mickits/__init__.py
mickits/__version__.py
mickits/csv.py
mickits/excel.py
mickits/json.py
mickits/mq.py
mickits/mysql_all_tables.py
mickits/mysql_create_table_statement.py
mickits/mysql_export_excel.py
mickits/qyweixin.py
mickits/sms.py
mickits/txt.py
mickits-0.1.51.dist-info/LICENSE
mickits-0.1.51.dist-info/METADATA
mickits-0.1.51.dist-info/WHEEL
mickits-0.1.51.dist-info/top_level.txt
mickits-0.1.51.dist-info/RECORD
