Metadata-Version: 2.1
Name: mickits
Version: 0.1.51
Summary: 日常工作使用的小工具/小功能
Home-page: https://www.infuq.com
Author: infuq
Author-email: 864511259@qq.com
License: MIT
Classifier: License :: OSI Approved :: MIT License
Classifier: Programming Language :: Python
Classifier: Programming Language :: Python :: 3
Classifier: Programming Language :: Python :: 3.6
Classifier: Programming Language :: Python :: Implementation :: CPython
Classifier: Programming Language :: Python :: Implementation :: PyPy
Requires-Python: >=3.6.0
License-File: LICENSE
